CHAP/TaskManager.py
CHAP/__init__.py
CHAP/models.py
CHAP/pipeline.py
CHAP/processor.py
CHAP/reader.py
CHAP/runner.py
CHAP/server.py
CHAP/writer.py
CHAP/common/__init__.py
CHAP/common/processor.py
CHAP/common/reader.py
CHAP/common/utils.py
CHAP/common/writer.py
CHAP/common/models/__init__.py
CHAP/common/models/common.py
CHAP/common/models/integration.py
CHAP/common/models/map.py
CHAP/edd/__init__.py
CHAP/edd/models.py
CHAP/edd/processor.py
CHAP/edd/reader.py
CHAP/edd/select_material_params_gui.py
CHAP/edd/utils.py
CHAP/edd/writer.py
CHAP/foxden/__init__.py
CHAP/foxden/models.py
CHAP/foxden/processor.py
CHAP/foxden/reader.py
CHAP/foxden/utils.py
CHAP/foxden/writer.py
CHAP/giwaxs/__init__.py
CHAP/giwaxs/models.py
CHAP/giwaxs/processor.py
CHAP/giwaxs/reader.py
CHAP/giwaxs/writer.py
CHAP/inference/__init__.py
CHAP/inference/processor.py
CHAP/inference/reader.py
CHAP/inference/writer.py
CHAP/saxswaxs/__init__.py
CHAP/saxswaxs/processor.py
CHAP/saxswaxs/reader.py
CHAP/saxswaxs/writer.py
CHAP/sin2psi/__init__.py
CHAP/sin2psi/processor.py
CHAP/sin2psi/reader.py
CHAP/sin2psi/writer.py
CHAP/tomo/__init__.py
CHAP/tomo/models.py
CHAP/tomo/processor.py
CHAP/tomo/reader.py
CHAP/tomo/writer.py
CHAP/utils/__init__.py
CHAP/utils/converters.py
CHAP/utils/fit.py
CHAP/utils/general.py
CHAP/utils/material.py
CHAP/utils/models.py
CHAP/utils/parfile.py
MLaaS/__init__.py
MLaaS/ktrain.py
MLaaS/mnist_img.py
MLaaS/tfaas_client.py
chessanalysispipeline-1.0.0.dist-info/LICENSE
chessanalysispipeline-1.0.0.dist-info/METADATA
chessanalysispipeline-1.0.0.dist-info/WHEEL
chessanalysispipeline-1.0.0.dist-info/entry_points.txt
chessanalysispipeline-1.0.0.dist-info/top_level.txt
chessanalysispipeline-1.0.0.dist-info/RECORD
