Metadata-Version: 2.1
Name: ChessAnalysisPipeline
Version: 1.0.0
Summary: CHESS analysis pipeline framework
Home-page: https://github.com/CHESSComputing/ChessAnalysisPipeline
Author: Keara Soloway, Rolf Verberg, Valentin Kuznetsov
Author-email: 
Classifier: Programming Language :: Python :: 3
Classifier: License :: OSI Approved :: MIT License
Classifier: Operating System :: OS Independent
Requires-Python: >=3.10
License-File: LICENSE
Requires-Dist: numpy
Requires-Dist: pydantic
Requires-Dist: pyyaml
